chatbox_modelscope_sync_mcp/__init__.py
chatbox_modelscope_sync_mcp/cli.py
chatbox_modelscope_sync_mcp/sync.py
chatbox_modelscope_sync_mcp-0.0.2.dist-info/licenses/LICENSE
mkgenerate/generate_docs.py
chatbox_modelscope_sync_mcp-0.0.2.dist-info/METADATA
chatbox_modelscope_sync_mcp-0.0.2.dist-info/WHEEL
chatbox_modelscope_sync_mcp-0.0.2.dist-info/entry_points.txt
chatbox_modelscope_sync_mcp-0.0.2.dist-info/top_level.txt
chatbox_modelscope_sync_mcp-0.0.2.dist-info/RECORD
