Metadata-Version: 2.4
Name: chatbox-modelscope-sync-mcp
Version: 0.0.2
Summary: 一键同步ModelScope MCP服务器到Chatbox配置的Python工具
Author-email: ztxtech <ztxtech@foxmail.com>
License: MIT License
Project-URL: Homepage, https://github.com/ztxtech/chatbox-modelscope-sync-mcp
Project-URL: Repository, https://github.com/ztxtech/chatbox-modelscope-sync-mcp
Project-URL: Documentation, https://github.com/ztxtech/chatbox-modelscope-sync-mcp#readme
Project-URL: Bug Tracker, https://github.com/ztxtech/chatbox-modelscope-sync-mcp/issues
Keywords: chatbox,modelscope,mcp,sync,automation,configuration,http-server
Classifier: Development Status :: 5 - Production/Stable
Classifier: Programming Language :: Python :: 3
Classifier: Programming Language :: Python :: 3.8
Classifier: Programming Language :: Python :: 3.9
Classifier: Programming Language :: Python :: 3.10
Classifier: Programming Language :: Python :: 3.11
Classifier: Programming Language :: Python :: 3.12
Classifier: License :: OSI Approved :: MIT License
Classifier: Operating System :: OS Independent
Classifier: Intended Audience :: Developers
Classifier: Intended Audience :: End Users/Desktop
Classifier: Topic :: Software Development :: Libraries :: Python Modules
Classifier: Topic :: System :: Systems Administration
Classifier: Topic :: Utilities
Requires-Python: >=3.8
License-File: LICENSE
Requires-Dist: requests
Requires-Dist: click
Provides-Extra: dev
Requires-Dist: pytest>=7.0; extra == "dev"
Requires-Dist: black>=22.0; extra == "dev"
Requires-Dist: isort>=5.0; extra == "dev"
Requires-Dist: flake8>=4.0; extra == "dev"
Requires-Dist: mypy>=0.900; extra == "dev"
Dynamic: license-file
